movies_module_micah/__init__.py
movies_module_micah-1.3.1.dist-info/LICENSE
movies_module_micah-1.3.1.dist-info/METADATA
movies_module_micah-1.3.1.dist-info/WHEEL
movies_module_micah-1.3.1.dist-info/top_level.txt
movies_module_micah-1.3.1.dist-info/RECORD
