Metadata-Version: 2.1
Name: movies-module-micah
Version: 1.3.1
Summary: Micah-specific exercise modules
Home-page: https://github.com/micang404/movies_module_micah
Author: Vincent
Author-email: micahkabala@outlook.com
License: UNKNOWN
Platform: UNKNOWN
Classifier: Programming Language :: Python :: 3
Classifier: License :: OSI Approved :: MIT License
Classifier: Operating System :: OS Independent
